viby/__init__.py
viby/cli/app.py
viby/cli/main.py
viby/commands/__init__.py
viby/commands/sessions.py
viby/commands/shortcuts.py
viby/commands/tools.py
viby/commands/vibe.py
viby/config/__init__.py
viby/config/app_config.py
viby/config/wizard.py
viby/llm/__init__.py
viby/llm/client.py
viby/llm/compaction.py
viby/llm/models.py
viby/llm/nodes/__init__.py
viby/llm/nodes/dummy_node.py
viby/llm/nodes/execute_tool_node.py
viby/llm/nodes/llm_node.py
viby/llm/nodes/prompt_node.py
viby/locale/__init__.py
viby/locale/en-US.yaml
viby/locale/zh-CN.yaml
viby/mcp/__init__.py
viby/mcp/client.py
viby/mcp/config.py
viby/tools/__init__.py
viby/tools/shell_tool.py
viby/tools/tool_retrieval.py
viby/utils/__init__.py
viby/utils/history.py
viby/utils/keyboard_shortcuts.py
viby/utils/lazy_import.py
viby/utils/logging.py
viby/utils/ui.py
viby/viby_tool_search/__init__.py
viby/viby_tool_search/client.py
viby/viby_tool_search/commands.py
viby/viby_tool_search/common.py
viby/viby_tool_search/embedding_manager.py
viby/viby_tool_search/server.py
viby/viby_tool_search/utils.py
viby-0.2.5.dist-info/licenses/LICENSE
viby-0.2.5.dist-info/METADATA
viby-0.2.5.dist-info/WHEEL
viby-0.2.5.dist-info/entry_points.txt
viby-0.2.5.dist-info/top_level.txt
viby-0.2.5.dist-info/RECORD
