Metadata-Version: 2.4
Name: viby
Version: 0.2.5
Summary: Viby vibes everything
Author-email: JohanLi233 <li_zhonghan@qq.com>
Requires-Python: >=3.10
License-File: LICENSE
Requires-Dist: fastapi>=0.115.12
Requires-Dist: fastmcp>=2.3.4
Requires-Dist: flatlatex>=0.15
Requires-Dist: numpy>=2.2.5
Requires-Dist: openai>=1.76.2
Requires-Dist: pocketflow>=0.0.2
Requires-Dist: prompt-toolkit>=3.0.51
Requires-Dist: pyperclip>=1.9.0
Requires-Dist: pyyaml>=6.0.2
Requires-Dist: requests>=2.32.3
Requires-Dist: rich>=14.0.0
Requires-Dist: sentence-transformers>=4.1.0
Requires-Dist: typer>=0.15.4
Provides-Extra: dev
Requires-Dist: black>=23.1.0; extra == "dev"
Requires-Dist: isort>=5.12.0; extra == "dev"
Requires-Dist: mypy>=1.0.1; extra == "dev"
Provides-Extra: test
Requires-Dist: pytest>=7.3.1; extra == "test"
Requires-Dist: pytest-cov>=4.1.0; extra == "test"
Requires-Dist: pytest-mock>=3.10.0; extra == "test"
Requires-Dist: coverage>=7.2.2; extra == "test"
Dynamic: license-file
